file_finder/__init__.py
file_finder/core.py
file_finder_utility-0.0.1.dist-info/licenses/LICENSE
file_finder_utility-0.0.1.dist-info/METADATA
file_finder_utility-0.0.1.dist-info/WHEEL
file_finder_utility-0.0.1.dist-info/entry_points.txt
file_finder_utility-0.0.1.dist-info/top_level.txt
file_finder_utility-0.0.1.dist-info/RECORD
